swagger_unittest/__init__.py
swagger_unittest/swagger_parser/__init__.py
swagger_unittest/swagger_parser/swagger_parser.py
swagger_unittest/swagger_tester/__init__.py
swagger_unittest/swagger_tester/swagger_tester.py
tests/__init__.py
tests/swagger_parser/__init__.py
tests/swagger_parser/conftest.py
tests/swagger_parser/test_swagger_parser.py
tests/swagger_parser/test_swagger_tester.py
swagger_unittest-0.3.6.dist-info/METADATA
swagger_unittest-0.3.6.dist-info/WHEEL
swagger_unittest-0.3.6.dist-info/top_level.txt
swagger_unittest-0.3.6.dist-info/RECORD
