Metadata-Version: 2.1
Name: swagger-unittest
Version: 0.3.6
Summary: Unittest swagger
Home-page: https://github.com/mild-blue/swagger-tester
Author: Mild Blue
Author-email: info@mild.blue
License: MIT
Download-URL: https://github.com/mild-blue/swagger-tester/releases/download/0.3.0/swagger-unittest-0.3.6.tar.gz
Keywords: utils swagger unittest
Platform: UNKNOWN
Classifier: Development Status :: 3 - Alpha
Classifier: Intended Audience :: Developers
Classifier: Topic :: Software Development :: Testing
Classifier: License :: OSI Approved :: MIT License
Classifier: Programming Language :: Python :: 3.7
Classifier: Programming Language :: Python :: 3.8
Classifier: Programming Language :: Python :: 3.9
Requires-Dist: attrs
Requires-Dist: jinja2
Requires-Dist: jsonschema
Requires-Dist: markupsafe
Requires-Dist: openapi-spec-validator
Requires-Dist: pyrsistent
Requires-Dist: pyyaml
Requires-Dist: six
Requires-Dist: werkzeug
Provides-Extra: dev
Requires-Dist: pre-commit ; extra == 'dev'
Provides-Extra: test
Requires-Dist: pytest ; extra == 'test'
Requires-Dist: requests ; extra == 'test'
